blister
