Metadata-Version: 1.1
Name: blister
Version: 1.0.1
Summary: Import hook that minimizes file stats
Home-page: https://gitlab.com/shredwheat/blister
Author: Peter Shinners
Author-email: pete@shinners.org
License: MIT
Keywords: import hook file stat disk
Platform: UNKNOWN
Classifier: Intended Audience :: Developers
Classifier: License :: OSI Approved :: MIT License
Classifier: Programming Language :: Python :: 2
